COPYING
README.rst
pyproject.toml
setup.cfg
setup.py
trash
trash-empty
trash-list
trash-put
trash-restore
trash-rm
man/man1/trash-empty.1
man/man1/trash-list.1
man/man1/trash-put.1
man/man1/trash-restore.1
man/man1/trash-rm.1
man/man1/trash.1
trash_cli.egg-info/PKG-INFO
trash_cli.egg-info/SOURCES.txt
trash_cli.egg-info/dependency_links.txt
trash_cli.egg-info/requires.txt
trash_cli.egg-info/top_level.txt
trashcli/__init__.py
trashcli/compat.py
trashcli/file_system_reader.py
trashcli/fs.py
trashcli/shell_completion.py
trashcli/trash.py
trashcli/trash_dirs_scanner.py
trashcli/empty/__init__.py
trashcli/empty/clock.py
trashcli/empty/console.py
trashcli/empty/delete_according_date.py
trashcli/empty/description.py
trashcli/empty/emptier.py
trashcli/empty/empty_action.py
trashcli/empty/empty_cmd.py
trashcli/empty/errors.py
trashcli/empty/existing_file_remover.py
trashcli/empty/file_system_dir_reader.py
trashcli/empty/guard.py
trashcli/empty/is_input_interactive.py
trashcli/empty/main.py
trashcli/empty/older_than.py
trashcli/empty/parse_reply.py
trashcli/empty/parser.py
trashcli/empty/prepare_output_message.py
trashcli/empty/print_time_action.py
trashcli/empty/top_trash_dir_rules_file_system_reader.py
trashcli/empty/user.py
trashcli/fstab/__init__.py
trashcli/fstab/mount_points_listing.py
trashcli/fstab/real_volume_of.py
trashcli/fstab/volume_listing.py
trashcli/fstab/volume_of.py
trashcli/fstab/volume_of_impl.py
trashcli/fstab/volumes.py
trashcli/lib/__init__.py
trashcli/lib/dir_checker.py
trashcli/lib/dir_reader.py
trashcli/lib/enum_repr.py
trashcli/lib/environ.py
trashcli/lib/exit_codes.py
trashcli/lib/logger.py
trashcli/lib/my_input.py
trashcli/lib/my_permission_error.py
trashcli/lib/path_of_backup_copy.py
trashcli/lib/print_version.py
trashcli/lib/trash_dir_reader.py
trashcli/lib/trash_dirs.py
trashcli/lib/user_info.py
trashcli/list/__init__.py
trashcli/list/extractors.py
trashcli/list/fs.py
trashcli/list/list_trash_action.py
trashcli/list/main.py
trashcli/list/parser.py
trashcli/list/trash_dir_selector.py
trashcli/list/minor_actions/__init__.py
trashcli/list/minor_actions/debug_volumes.py
