Metadata-Version: 2.1
Name: trash-cli
Version: 0.24.5.26
Summary: Command line interface to FreeDesktop.org Trash.
Home-page: https://github.com/andreafrancia/trash-cli
Author: Andrea Francia
Author-email: andrea@andreafrancia.it
License: GPL v2
License-File: COPYING
Requires-Dist: psutil
Requires-Dist: six
Requires-Dist: typing; python_version < "3.8"
Requires-Dist: typing_extensions; python_version < "3.8"
Requires-Dist: enum34; python_version < "3.4"
Provides-Extra: completion
Requires-Dist: shtab; extra == "completion"
